pipeline_deploy/__init__.py
pipeline_deploy/cli.py
pipeline_deploy/click_types.py
pipeline_deploy/controllers.py
pipeline_deploy/utils.py
pipeline_deploy/version.py
pipeline_deploy/configure/__init__.py
pipeline_deploy/configure/config.py
pipeline_deploy/databricks/__init__.py
pipeline_deploy/databricks/cli.py
pipeline_deploy/databricks/controllers.py
pipeline_deploy/databricks/utils.py
pipeline_deploy/databricks/configure/__init__.py
pipeline_deploy/databricks/configure/config.py
pipeline_deploy-0.3.5.dist-info/LICENSE
pipeline_deploy-0.3.5.dist-info/METADATA
pipeline_deploy-0.3.5.dist-info/NOTICE.md
pipeline_deploy-0.3.5.dist-info/WHEEL
pipeline_deploy-0.3.5.dist-info/entry_points.txt
pipeline_deploy-0.3.5.dist-info/top_level.txt
pipeline_deploy-0.3.5.dist-info/RECORD
