Metadata-Version: 2.1
Name: pipeline-deploy
Version: 0.3.5
Summary: A deployment tool for ETL data pipelines.
Home-page: https://github.com/comcast/pipeline-deploy
Author: Jordan Yaker
Author-email: jordan_yaker@comcast.com
License: Apache License 2.0
Keywords: etl data pipeline databricks deploy cli devops
Platform: UNKNOWN
Classifier: Intended Audience :: Developers
Classifier: Intended Audience :: System Administrators
Classifier: Programming Language :: Python :: 3.7
Classifier: License :: OSI Approved :: Apache Software License
License-File: LICENSE
License-File: NOTICE.md
Requires-Dist: click (>=6.7)
Requires-Dist: databricks-cli (>=0.14.3)
